jsonschema_model.py
jsonschema_model-1.4.0.dist-info/pbr.json
jsonschema_model-1.4.0.dist-info/METADATA
jsonschema_model-1.4.0.dist-info/metadata.json
jsonschema_model-1.4.0.dist-info/DESCRIPTION.rst
jsonschema_model-1.4.0.dist-info/top_level.txt
jsonschema_model-1.4.0.dist-info/RECORD
jsonschema_model-1.4.0.dist-info/WHEEL
