Metadata-Version: 2.0
Name: jsonschema-model
Version: 1.4.0
Summary: Json schema Model
Home-page: https://github.com/philpep/jsonschema-model
Author: Philippe Pepiot
Author-email: phil@philpep.org
License: BSD
Platform: UNKNOWN
